{
  "projectId": "gen-lang-client-0009572581",
  "appId": "1:958839183835:web:80cec81bbb0227f7b82ffe",
  "apiKey": "AIzaSyBsHLGN0kujwUzvNMTqKZkMhx5C5_Yv6z8",
  "authDomain": "gen-lang-client-0009572581.firebaseapp.com",
  "firestoreDatabaseId": "ai-studio-zana-61fd6b5f-d052-40d1-8657-de471d642e8c",
  "storageBucket": "gen-lang-client-0009572581.firebasestorage.app",
  "messagingSenderId": "958839183835",
  "measurementId": "",
  "oAuthClientId": "958839183835-3bc7tgfegi6ohldn6imvj7l9goombl6d.apps.googleusercontent.com",
  "recaptchaSiteKey": ""
}